usefuladbpluswithrestart/README.MD
usefuladbpluswithrestart/__init__.py
usefuladbpluswithrestart/requirements.txt
usefuladbpluswithrestart/thirdparty.json
usefuladbpluswithrestart-0.10.dist-info/LICENSE.rst
usefuladbpluswithrestart-0.10.dist-info/METADATA
usefuladbpluswithrestart-0.10.dist-info/WHEEL
usefuladbpluswithrestart-0.10.dist-info/top_level.txt
usefuladbpluswithrestart-0.10.dist-info/RECORD
